autotorrent/__init__.py
autotorrent/at.py
autotorrent/autotorrent.conf.dist
autotorrent/bencode.py
autotorrent/cmd.py
autotorrent/db.py
autotorrent/humanize.py
autotorrent/scgitransport.py
autotorrent/utils.py
autotorrent/clients/__init__.py
autotorrent/clients/_base.py
autotorrent/clients/deluge.py
autotorrent/clients/rtorrent.py
autotorrent/clients/transmission.py
autotorrent-1.6.4.dist-info/DESCRIPTION.rst
autotorrent-1.6.4.dist-info/METADATA
autotorrent-1.6.4.dist-info/RECORD
autotorrent-1.6.4.dist-info/WHEEL
autotorrent-1.6.4.dist-info/entry_points.txt
autotorrent-1.6.4.dist-info/metadata.json
autotorrent-1.6.4.dist-info/top_level.txt
