Metadata-Version: 2.0
Name: autotorrent
Version: 1.6.4
Summary: AutoTorrent allows easy cross-seeding
Home-page: https://github.com/JohnDoee/autotorrent
Author: John Doee
Author-email: johndoee+autotorrent@tidalstream.org
License: MIT
Platform: UNKNOWN
Classifier: Development Status :: 4 - Beta
Classifier: Environment :: Console
Classifier: Intended Audience :: End Users/Desktop
Classifier: License :: OSI Approved :: MIT License
Classifier: Operating System :: POSIX :: BSD
Classifier: Operating System :: POSIX :: Linux
Classifier: Operating System :: POSIX :: Other
Classifier: Programming Language :: Python :: 2.7
Classifier: Programming Language :: Python :: 3
Classifier: Programming Language :: Python :: 3.3
Classifier: Programming Language :: Python :: 3.4
Classifier: Programming Language :: Python :: 3.5
Classifier: Programming Language :: Python :: 3.6
Classifier: Topic :: Communications :: File Sharing
Requires-Dist: six
Requires-Dist: deluge-client
Requires-Dist: requests
